vease_back/__init__.py
vease_back/app.py
vease_back/py.typed
vease_back/routes/blueprint_vease.py
vease_back/routes/schemas/__init__.py
vease_back/routes/schemas/healthcheck.json
vease_back/routes/schemas/healthcheck.py
vease_back/routes/schemas/microservice_version.json
vease_back/routes/schemas/microservice_version.py
vease_back/routes/schemas/packages_versions.json
vease_back/routes/schemas/packages_versions.py
vease_back-1.8.0.dist-info/licenses/LICENSE
vease_back-1.8.0.dist-info/METADATA
vease_back-1.8.0.dist-info/WHEEL
vease_back-1.8.0.dist-info/entry_points.txt
vease_back-1.8.0.dist-info/top_level.txt
vease_back-1.8.0.dist-info/RECORD
